UIE/UCErrors.py
UIE/__init__.py
UIE/modes.py
UIE/uiecoder.py
UIE-1.0.1.dist-info/LICENSE
UIE-1.0.1.dist-info/METADATA
UIE-1.0.1.dist-info/WHEEL
UIE-1.0.1.dist-info/top_level.txt
UIE-1.0.1.dist-info/RECORD
