Metadata-Version: 2.1
Name: UIE
Version: 1.0.1
Summary: An encrypting algorithm
Home-page: https://github.com/policere/UIE
Author: ftdot
Author-email: ftdoot@gmail.com
License: UNKNOWN
Platform: UNKNOWN
Classifier: Programming Language :: Python :: 3
Classifier: License :: OSI Approved :: MIT License
Classifier: Operating System :: OS Independent
License-File: LICENSE
